setup.py
Fosbury.egg-info/PKG-INFO
Fosbury.egg-info/SOURCES.txt
Fosbury.egg-info/dependency_links.txt
Fosbury.egg-info/top_level.txt
fosbury/__init__.py
fosbury/errors.py
fosbury.egg-info/SOURCES.txt