Metadata-Version: 1.0
Name: Fosbury
Version: 0.9.6
Summary: Python client for Fosbury (http://fosbury.co)
Home-page: UNKNOWN
Author: Willem Spruijt
Author-email: willem@fosbury.co
License: Apache License 2.0
Platform: UNKNOWN
